{"stats":{"minecraft:mined":{"tboi_suzu:basement_wall":3,"tboi_suzu:spikes":7},"minecraft:killed":{"tboi_suzu:samson":1,"tboi_suzu:magdalene":1,"tboi_suzu:judas":1,"tboi_suzu:isaac":14,"tboi_suzu:blue_baby":1,"minecraft:slime":9,"tboi_suzu:eva":2,"tboi_suzu:eva_whore_of_babylon":2,"minecraft:zombie":1,"tboi_suzu:cain":1,"tboi_suzu:azazel":3,"minecraft:cow":3},"minecraft:killed_by":{"tboi_suzu:eva_whore_of_babylon":1},"minecraft:custom":{"minecraft:mob_kills":38,"minecraft:play_record":3,"minecraft:leave_game":20,"minecraft:time_since_death":16327,"minecraft:damage_resisted":870,"minecraft:time_since_rest":16350,"minecraft:sprint_one_cm":434653,"minecraft:damage_taken":3930,"minecraft:walk_one_cm":536801,"minecraft:drop":48,"minecraft:damage_dealt":3961,"minecraft:talked_to_villager":2,"minecraft:fly_one_cm":1648042,"minecraft:crouch_one_cm":3318,"minecraft:play_time":491265,"minecraft:deaths":20,"minecraft:sneak_time":2097,"minecraft:jump":1216,"minecraft:total_world_time":911188,"minecraft:fall_one_cm":10802},"minecraft:dropped":{"minecraft:enchanted_book":1,"tboi_suzu:basement_floor":1,"tboi_suzu:red_heart":1,"tboi_suzu:nickel":9,"tboi_suzu:dime":3,"tboi_suzu:key":1,"minecraft:leather":2,"tboi_suzu:penny":16,"minecraft:grass_block":3,"tboi_suzu:cracked_dice":1,"minecraft:structure_void":1,"tboi_suzu:blood_penny":1,"minecraft:stone":1,"tboi_suzu:silver_dollar":7,"tboi_suzu:charged_the_fool":1,"minecraft:slime_ball":4,"minecraft:beef":5,"minecraft:magma_block":2},"minecraft:used":{"minecraft:oak_trapdoor":3,"minecraft:water_bucket":1,"minecraft:netherite_sword":51,"tboi_suzu:blue_baby_spawn_egg":1,"minecraft:cow_spawn_egg":8,"minecraft:pufferfish_spawn_egg":1,"tboi_suzu:blood_machine":7,"minecraft:stone":189,"minecraft:structure_void":68,"tboi_suzu:magdalene_spawn_egg":1,"tboi_suzu:slot_machine":5,"minecraft:structure_block":20,"minecraft:oak_door":6,"tboi_suzu:basement_wall":1645,"minecraft:torch":1,"minecraft:dirt":3,"minecraft:ancient_debris":2,"minecraft:campfire":117,"tboi_suzu:basement_floor":570,"tboi_suzu:red_chest":2,"minecraft:milk_bucket":1,"minecraft:black_concrete":3,"tboi_suzu:cain_spawn_egg":1,"minecraft:lava_bucket":74,"tboi_suzu:judas_spawn_egg":1,"minecraft:grass_block":70,"minecraft:barrier":2,"minecraft:stone_button":1,"minecraft:spawner":6,"tboi_suzu:angel_chest":4,"tboi_suzu:devils_cobblestone":11,"minecraft:item_frame":49,"tboi_suzu:azazel_spawn_egg":3,"tboi_suzu:normal_chest":3,"minecraft:slime_spawn_egg":3,"minecraft:bedrock":1,"tboi_suzu:beggar_spawn_egg":3,"minecraft:magma_block":16,"tboi_suzu:mark_stone":15,"tboi_suzu:isaac_spawn_egg":14,"tboi_suzu:golden_chest":5,"tboi_suzu:gaper_spawn_egg":9,"minecraft:netherite_pickaxe":4,"tboi_suzu:basement_structure_block":14,"minecraft:stone_pressure_plate":5,"tboi_suzu:eva_spawn_egg":1,"minecraft:jukebox":1,"tboi_suzu:spikes":129},"minecraft:picked_up":{"tboi_suzu:dime":7,"tboi_suzu:penny":35,"minecraft:leather":2,"tboi_suzu:blended_heart":1,"minecraft:enchanted_book":1,"tboi_suzu:charged_the_sun":1,"minecraft:gunpowder":2,"tboi_suzu:the_lovers":1,"minecraft:dirt":92,"tboi_suzu:the_magician":2,"minecraft:item_frame":2,"tboi_suzu:spikes":7,"tboi_suzu:pill_10":2,"tboi_suzu:pill_12":1,"tboi_suzu:silver_dollar":7,"minecraft:beef":5,"tboi_suzu:the_hermit":1,"tboi_suzu:golden_chest":1,"tboi_suzu:nickel":15,"tboi_suzu:eternal_heart":1,"tboi_suzu:charged_the_high_priestess":1,"tboi_suzu:charged_the_fool":1,"tboi_suzu:black_heart":1,"tboi_suzu:red_heart":53,"tboi_suzu:basement_wall":9,"tboi_suzu:pill_7":1,"tboi_suzu:death":1,"tboi_suzu:big_bomb":1,"tboi_suzu:soul_heart":8,"minecraft:grass_block":1,"tboi_suzu:charged_strengh":1,"minecraft:slime_ball":4,"tboi_suzu:key":16,"tboi_suzu:blood_penny":2,"tboi_suzu:the_empress":1,"tboi_suzu:charged_the_hierophant":1,"tboi_suzu:bomb":23}},"DataVersion":3465}